luna/__init__.py
luna/base_bot.py
luna/cli.py
luna/dual_piper.py
luna/model_server.py
luna/policy_client.py
luna/run.py
luna/configs/__init__.py
luna/configs/run_config.py
luna/gemma/__init__.py
luna/gemma/configuration_gemma.py
luna/gemma/modeling_flax_gemma.py
luna/gemma/modeling_gemma.py
luna/gemma/modular_gemma.py
luna/gemma/tokenization_gemma.py
luna/gemma/tokenization_gemma_fast.py
luna/layers/__init__.py
luna/layers/attention.py
luna/layers/linear.py
luna/layers/rope.py
luna/lerobot_dev/__init__.py
luna/lerobot_dev/robots/__init__.py
luna/lerobot_dev/robots/bi_piper_follower/__init__.py
luna/lerobot_dev/robots/bi_piper_follower/bi_piper_follower.py
luna/lerobot_dev/robots/bi_piper_follower/bi_piper_follower_eepose.py
luna/lerobot_dev/robots/bi_piper_follower/config_bi_piper_follower.py
luna/lerobot_dev/robots/bi_piper_follower/config_bi_piper_follower_eepose.py
luna/lerobot_dev/robots/piper_follower/__init__.py
luna/lerobot_dev/robots/piper_follower/config_piper_follower.py
luna/lerobot_dev/robots/piper_follower/piper_bus.py
luna/lerobot_dev/robots/piper_follower/piper_follower.py
luna/paligemma/__init__.py
luna/paligemma/configuration_paligemma.py
luna/paligemma/modeling_paligemma.py
luna/paligemma/processing_paligemma.py
luna/policies/__init__.py
luna/policies/factory.py
luna/policies/normalize.py
luna/policies/pi05/__init__.py
luna/policies/pi05/configuration_pi05.py
luna/policies/pi05/modeling_pi05.py
luna/policies/pi05/utils.py
luna/policies/starvla/__init__.py
luna/policies/starvla/internvl_dit.py
luna/robots/__init__.py
luna/robots/bi_piper_follower_adapter.py
luna2-0.1.5.dist-info/licenses/LICENSE
luna2-0.1.5.dist-info/METADATA
luna2-0.1.5.dist-info/WHEEL
luna2-0.1.5.dist-info/entry_points.txt
luna2-0.1.5.dist-info/top_level.txt
luna2-0.1.5.dist-info/RECORD
