Metadata-Version: 2.4
Name: luna2
Version: 0.1.5
Summary: Real-Time VLAs via Future-state-aware Asynchronous Inference.
Author: Jin Fagang
License: MIT
Project-URL: Homepage, https://github.com/jinfagang/luna
Project-URL: Repository, https://github.com/jinfagang/luna
Classifier: Development Status :: 3 - Alpha
Classifier: Intended Audience :: Developers
Classifier: License :: OSI Approved :: MIT License
Classifier: Programming Language :: Python :: 3
Classifier: Programming Language :: Python :: 3.8
Classifier: Programming Language :: Python :: 3.9
Classifier: Programming Language :: Python :: 3.10
Classifier: Programming Language :: Python :: 3.11
Classifier: Programming Language :: Python :: 3.12
Classifier: Programming Language :: Python :: 3.13
Requires-Python: >=3.10
License-File: LICENSE
Requires-Dist: lerobot[feetech,smolvla]==0.4.1
Requires-Dist: transformers
Requires-Dist: peft>=0.18.0
Requires-Dist: bitsandbytes>=0.48.2
Requires-Dist: flask>=3.1.2
Requires-Dist: flask-cors>=4.0.0
Requires-Dist: requests>=2.31.0
Requires-Dist: reachy2_sdk
Requires-Dist: superbot2
Requires-Dist: loguru
Dynamic: license-file
